lyrixir/__init__.py
lyrixir/__main__.py
lyrixir/config.py
lyrixir/fancy.py
lyrixir/lyrixir.py
lyrixir/lyrixir_add.py
lyrixir/lyrixir_list.py
lyrixir/lyrixir_remove.py
lyrixir/main.py
lyrixir/paths.py
lyrixir/songs.py
lyrixir-0.1.0.dist-info/METADATA
lyrixir-0.1.0.dist-info/WHEEL
lyrixir-0.1.0.dist-info/entry_points.txt
lyrixir-0.1.0.dist-info/licenses/LICENSE
lyrixir-0.1.0.dist-info/RECORD
